README
setup.py
libgmbox/__init__.py
libgmbox/const.py
libgmbox/core.py
libgmbox/test.py
libgmbox/utility.py
libgmbox.egg-info/PKG-INFO
libgmbox.egg-info/SOURCES.txt
libgmbox.egg-info/dependency_links.txt
libgmbox.egg-info/top_level.txt