Metadata-Version: 1.0
Name: libgmbox
Version: 1.0
Summary: 谷歌音乐解析库
Home-page: UNKNOWN
Author: muzuiget
Author-email: muzuiget@gmail.com
License: GPL
Platform: UNKNOWN
